{
  "data": [
    {
      "voaid": "4024",
      "EndTiming": "2.9",
      "Paraid": "1",
      "IdIndex": "1",
      "Timing": "0.5",
      "Sentence_cn": "课文24  美",
      "Sentence": "--- Lesson 24 Beauty"
    },
    {
      "voaid": "4024",
      "EndTiming": "14.9",
      "Paraid": "1",
      "IdIndex": "2",
      "Timing": "3.8",
      "Sentence_cn": "在大自然或艺术中瞥见美，常常会给人的心灵带来什么启示? ",
      "Sentence": "What do glimpses of beauty, either in nature or art, often suggest to the human mind?"
    },
    {
      "voaid": "4024",
      "EndTiming": "20.1",
      "Paraid": "1",
      "IdIndex": "3",
      "Timing": "17.4",
      "Sentence_cn": "一个年轻人看到日落，",
      "Sentence": "A young man sees a sunset and,"
    },
    {
      "voaid": "4024",
      "EndTiming": "24.7",
      "Paraid": "1",
      "IdIndex": "4",
      "Timing": "20.1",
      "Sentence_cn": "由于无法理解和表达日落在他心中唤起的激情，",
      "Sentence": "unable to understand or to express the emotion that it rouses in him,"
    },
    {
      "voaid": "4024",
      "EndTiming": "29.3",
      "Paraid": "1",
      "IdIndex": "5",
      "Timing": "25.2",
      "Sentence_cn": "便得出结论：日落处想必是通往遥远世界的大门。",
      "Sentence": "concludes that it must be the gateway to a world that lies beyond"
    },
    {
      "voaid": "4024",
      "EndTiming": "35.1",
      "Paraid": "1",
      "IdIndex": "6",
      "Timing": "30.0",
      "Sentence_cn": "无论是谁，在强烈感受到美的时刻，",
      "Sentence": "It is difficult for any of us in moments of intense aesthetic experience"
    },
    {
      "voaid": "4024",
      "EndTiming": "39.4",
      "Paraid": "1",
      "IdIndex": "7",
      "Timing": "35.4",
      "Sentence_cn": "心中都不禁油生一种遐想：",
      "Sentence": "to resist the suggestion that we are catching a glimpse of a light"
    },
    {
      "voaid": "4024",
      "EndTiming": "45.5",
      "Paraid": "1",
      "IdIndex": "8",
      "Timing": "39.6",
      "Sentence_cn": "我们似乎瞥见从另一个世界射向我们的一线光芒，那个世界不仅不同于我们这个世界，",
      "Sentence": "that shines down to us from a different realm of existence, different and,"
    },
    {
      "voaid": "4024",
      "EndTiming": "50.5",
      "Paraid": "1",
      "IdIndex": "9",
      "Timing": "45.5",
      "Sentence_cn": "而且由于美感的强烈感染，在某些方面比我们这个世界更美好。",
      "Sentence": "because the experience is intensely moving, in some way higher."
    },
    {
      "voaid": "4024",
      "EndTiming": "57.2",
      "Paraid": "1",
      "IdIndex": "10",
      "Timing": "51.1",
      "Sentence_cn": "虽然这光芒令人眼花缭乱，但它确实给予我们一种美感和静谧的启示。",
      "Sentence": "And, though the gleams blind and dazzle, yet do they convey a hint of beauty and serenity"
    },
    {
      "voaid": "4024",
      "EndTiming": "62.5",
      "Paraid": "1",
      "IdIndex": "11",
      "Timing": "57.5",
      "Sentence_cn": "这是我们不曾经历和无法想象的。这种美感和静谧是我们无法描述的，",
      "Sentence": "greater than we have known or imagined. Greater too than we can describe;"
    },
    {
      "voaid": "4024",
      "EndTiming": "67.8",
      "Paraid": "1",
      "IdIndex": "12",
      "Timing": "63.1",
      "Sentence_cn": "因为我们发明的语言是用来描述这个世界的含义，",
      "Sentence": "for language, which was invented to convey the meanings of this world"
    },
    {
      "voaid": "4024",
      "EndTiming": "71.3",
      "Paraid": "1",
      "IdIndex": "13",
      "Timing": "68.0",
      "Sentence_cn": "不能随便拿来去描述另一个世界。",
      "Sentence": "cannot readily be fitted to the uses of another."
    },
    {
      "voaid": "4024",
      "EndTiming": "79.3",
      "Paraid": "1",
      "IdIndex": "14",
      "Timing": "72.8",
      "Sentence_cn": "不可否认，一切伟大的艺术都具有使人遐想到进入天外世界的魅力。",
      "Sentence": "That all great art has this power of suggesting a world beyond is undeniable."
    },
    {
      "voaid": "4024",
      "EndTiming": "82.8",
      "Paraid": "1",
      "IdIndex": "15",
      "Timing": "79.9",
      "Sentence_cn": "在某种状态下，大自然也有这种魅力。",
      "Sentence": "In some moods, nature shares it."
    },
    {
      "voaid": "4024",
      "EndTiming": "88.5",
      "Paraid": "1",
      "IdIndex": "16",
      "Timing": "83.5",
      "Sentence_cn": "六月蔚蓝的天空总使人遥想一个更加蔚蓝的苍穹；",
      "Sentence": "There is no sky in June so blue that it does not point forward to a bluer,"
    },
    {
      "voaid": "4024",
      "EndTiming": "94.3",
      "Paraid": "1",
      "IdIndex": "17",
      "Timing": "89.2",
      "Sentence_cn": "美丽的落日总会引起一个更加绚丽的景象",
      "Sentence": "no sunset so beautiful that it does not waken the vision of a greater beauty,"
    },
    {
      "voaid": "4024",
      "EndTiming": "98.1",
      "Paraid": "1",
      "IdIndex": "18",
      "Timing": "94.7",
      "Sentence_cn": "未及饱览便一闪即逝，",
      "Sentence": "a vision which passes before it is fully glimpsed,"
    },
    {
      "voaid": "4024",
      "EndTiming": "102.1",
      "Paraid": "1",
      "IdIndex": "19",
      "Timing": "98.1",
      "Sentence_cn": "并在消逝中给人留下不可名状的渴望和惆怅。",
      "Sentence": "and in passing leaves an indefinable longing and regret."
    },
    {
      "voaid": "4024",
      "EndTiming": "105.6",
      "Paraid": "1",
      "IdIndex": "20",
      "Timing": "102.6",
      "Sentence_cn": "如果这个世界不只是一个拙劣的恶作剧，",
      "Sentence": "But, if this world is not merely a bad joke,"
    },
    {
      "voaid": "4024",
      "EndTiming": "109.8",
      "Paraid": "1",
      "IdIndex": "21",
      "Timing": "106.0",
      "Sentence_cn": "如果人生不只是群星寒光中平凡的一闪，",
      "Sentence": "life a vulgar flare amid the cool radiance of the stars,"
    },
    {
      "voaid": "4024",
      "EndTiming": "114.5",
      "Paraid": "1",
      "IdIndex": "22",
      "Timing": "110.2",
      "Sentence_cn": "如果存在不只是对神秘事物的一种空虚的笑声，",
      "Sentence": "and existence an empty laugh braying across the mysteries;"
    },
    {
      "voaid": "4024",
      "EndTiming": "118.8",
      "Paraid": "1",
      "IdIndex": "23",
      "Timing": "114.5",
      "Sentence_cn": "如果某种玄妙事物的暗示",
      "Sentence": "if these intimations of a something behind and beyond"
    },
    {
      "voaid": "4024",
      "EndTiming": "122.7",
      "Paraid": "1",
      "IdIndex": "24",
      "Timing": "119.2",
      "Sentence_cn": "不是消化不良引起的邪恶情绪，",
      "Sentence": "are not evil humour born of indigestion,"
    },
    {
      "voaid": "4024",
      "EndTiming": "128.6",
      "Paraid": "1",
      "IdIndex": "25",
      "Timing": "123.0",
      "Sentence_cn": "也不是魔鬼为了捉弄我们，使我们发狂而送给我们的邪念，一句话，",
      "Sentence": "or whimsies sent by the devil to mock and madden us, if, in a word"
    },
    {
      "voaid": "4024",
      "EndTiming": "133.8",
      "Paraid": "1",
      "IdIndex": "26",
      "Timing": "128.8",
      "Sentence_cn": "如果美有某种意义的话，我闪千万不要去阐明它的意义。",
      "Sentence": "beauty means something yet we must not seek to interpret the meaning."
    },
    {
      "voaid": "4024",
      "EndTiming": "139.6",
      "Paraid": "1",
      "IdIndex": "27",
      "Timing": "134.7",
      "Sentence_cn": "如果我瞥见了只可意会不可言传的事物，企图把它说出来，那上不明智的；",
      "Sentence": "If we glimpse the unutterable, it is unwise to try to utter it,"
    },
    {
      "voaid": "4024",
      "EndTiming": "145.2",
      "Paraid": "1",
      "IdIndex": "28",
      "Timing": "139.8",
      "Sentence_cn": "对于我们不理解的事物，我们也不应该去赋予它某种意义。",
      "Sentence": "nor should we seek to invest with significance that which we cannot grasp."
    },
    {
      "voaid": "4024",
      "EndTiming": "158.2",
      "Paraid": "1",
      "IdIndex": "29",
      "Timing": "146.1",
      "Sentence_cn": "用对我们人类有意义的词解释美是没有意义的。",
      "Sentence": "Beauty in terms of our human meanings is meaningless."
    }
  ],
  "size": 29,
  "title": {
    "newCategoryid": 1154,
    "newTitleId": "14765,14766,14767,14768",
    "title_cn": "美",
    "title": "Beauty"
  },
  "audio_us": "https://static.aienglish.com/static2/newconcept/4_24.mp3"
}